vkmusix/__init__.py
vkmusix/aio.py
vkmusix/base.py
vkmusix/client.py
vkmusix/config.py
vkmusix/utils.py
vkmusix/version.py
vkmusix/web.py
vkmusix/webClient.py
vkmusix/enums/__init__.py
vkmusix/enums/extension.py
vkmusix/enums/language.py
vkmusix/enums/playlistType.py
vkmusix/errors/__init__.py
vkmusix/errors/accessDenied.py
vkmusix/errors/chatNotFound.py
vkmusix/errors/error.py
vkmusix/errors/invalidMethod.py
vkmusix/errors/invalidProxyDict.py
vkmusix/errors/invalidProxyType.py
vkmusix/errors/mp3FileNotFound.py
vkmusix/errors/mp3FileTooBig.py
vkmusix/errors/noneQuery.py
vkmusix/errors/notFound.py
vkmusix/errors/ownerIdsAndTrackIdsLenDifferent.py
vkmusix/errors/ownerIdsAndTrackIdsTypeDifferent.py
vkmusix/errors/ruCaptchaBannedAccount.py
vkmusix/errors/ruCaptchaBannedIP.py
vkmusix/errors/ruCaptchaInvalidKey.py
vkmusix/errors/ruCaptchaZeroBalance.py
vkmusix/errors/sessionAlreadyClosed.py
vkmusix/errors/sessionAlreadyOpened.py
vkmusix/errors/sessionClosed.py
vkmusix/errors/tooHighRequestSendingRate.py
vkmusix/errors/trackReorderNeedsBeforeOrAfterArgument.py
vkmusix/errors/trackReorderNeedsOnlyBeforeOrAfterNotBoth.py
vkmusix/errors/trackRestorationTimeEnded.py
vkmusix/errors/unknown.py
vkmusix/errors/userWasDeletedOrBanned.py
vkmusix/errors/vkInvalidToken.py
vkmusix/methods/__init__.py
vkmusix/methods/artists/__init__.py
vkmusix/methods/artists/followArtist.py
vkmusix/methods/artists/getArtist.py
vkmusix/methods/artists/getArtistAlbums.py
vkmusix/methods/artists/getArtistTracks.py
vkmusix/methods/artists/getRelatedArtists.py
vkmusix/methods/artists/unfollowArtist.py
vkmusix/methods/curators/__init__.py
vkmusix/methods/curators/followCurator.py
vkmusix/methods/curators/getCuratorTracks.py
vkmusix/methods/curators/unfollowCurator.py
vkmusix/methods/misc/__init__.py
vkmusix/methods/misc/api.py
vkmusix/methods/misc/getMe.py
vkmusix/methods/other/__init__.py
vkmusix/methods/other/_getTracks.py
vkmusix/methods/other/api.py
vkmusix/methods/other/getMe.py
vkmusix-4.4.2.dist-info/LICENSE
vkmusix-4.4.2.dist-info/METADATA
vkmusix-4.4.2.dist-info/WHEEL
vkmusix-4.4.2.dist-info/top_level.txt
vkmusix-4.4.2.dist-info/RECORD
